{
  "addr": "0x278f5d89c85a4ac8aaa39e08444212cbb2546fd2",
  "decimals": 18,
  "description": "Carlos Matos Coin (HEY) its a revolutionary coin who is changing the world as we know it.",
  "links": [
    {
      "Twitter": "https://twitter.com/MatosCoin"
    },
    {
      "Website": "https://carlosco.in/"
    },
    {
      "YouTube": "https://www.youtube.com/watch?v=MQCLH8vvt6E"
    },
    {
      "YouTube": "https://www.youtube.com/watch?v=PDiSLXcAU3U"
    },
    {
      "YouTube": "https://www.youtube.com/watch?v=1tQ8MYyApPU"
    },
    {
      "Bitcointalk": "https://bitcointalk.org/index.php?topic=2994076.0"
    }
  ],
  "name": "Carlos Matos Token",
  "symbol": "HEY"
}