{
  "addr": "0x6888a16ea9792c15a4dcf2f6c623d055c8ede792",
  "decimals": 18,
  "description": "The Signal Token (SIG) Protocol is designed to decentralize the buying, selling, and rewarding of attention across media platforms by removing centralized intermediaries from advertising transactions.",
  "links": [
    {
      "Blog": "https://medium.com/spectiv-vr"
    },
    {
      "Facebook": "https://www.facebook.com/spectivvr/"
    },
    {
      "Github": "https://github.com/spectivofficial"
    },
    {
      "Telegram": "https://t.me/spectivtelegram"
    },
    {
      "Twitter": "https://twitter.com/spectivvr"
    },
    {
      "Website": "https://www.spectivvr.com"
    },
    {
      "Whitepaper": "https://drive.google.com/file/d/1-Y4-Bb9-70DhdVeTvYLZtkK5W3Lvruc-/view?usp=sharing"
    }
  ],
  "name": "Signals",
  "symbol": "SIG"
}