{
  "addr": "0xaa26b73bfdc80b5c7d2cfbfc30930038fb7fa657",
  "decimals": 0,
  "description": "The intent of Tokenverse is to bring blockchain and crypto within reach and understanding of the everyday person through the content generated by the syndication network. News. Journalism. Podcasts. Essays. Interviews. We want the network to provide a variety of content that can appeal to the widest possible spectrum of visitors.\nWe will also provide services to projects looking to boost their signal. These include ad space, interviews, listings, etc. We will continue to explore more ways to be of use to the community, and we will always consider any ideas the community proposes.",
  "links": [
    {
      "Website": "http://www.tokenverse.com/services/"
    }
  ],
  "name": "TokenVerse",
  "symbol": "TOV"
}